{"id": "v177393650", "title": "Reckful - Barcelona, Spain last day", "duration": 9413, "thumbnail": "https://static-cdn.jtvnw.net/cf_vods/d2nvs31859zcd8/89a8bdc0bb1f80665b01_reckful_26337123088_714740384/thumb/thumb0-90x60.jpg", "uploader": "Reckful", "uploader_id": "reckful", "timestamp": 1506344390, "view_count": 13375, "chapters": [], "is_live": false, "was_live": true, "formats": [{"format_id": "sb1", "format_note": "storyboard", "ext": "mhtml", "protocol": "mhtml", "acodec": "none", "vcodec": "none", "url": "https://d2nvs31859zcd8.cloudfront.net/89a8bdc0bb1f80665b01_reckful_26337123088_714740384/storyboards/177393650-low-0.jpg", "width": 110, "height": 62, "fps": 0.020928503133963668, "rows": 40, "columns": 5, "fragments": [{"url": "https://d2nvs31859zcd8.cloudfront.net/89a8bdc0bb1f80665b01_reckful_26337123088_714740384/storyboards/177393650-low-0.jpg", "duration": 9413.0}], "resolution": "110x62", "aspect_ratio": 1.77, "http_headers": {"User-Agent": "Mozilla/5.0 (Windows NT 10.0; Win64; x64) AppleWebKit/537.36 (KHTML, like Gecko) Chrome/94.0.4606.54 Safari/537.36", "Accept": "text/html,application/xhtml+xml,application/xml;q=0.9,*/*;q=0.8", "Accept-Language": "en-us,en;q=0.5", "Sec-Fetch-Mode": "navigate"}, "audio_ext": "none", "video_ext": "none", "format": "sb1 - 110x62 (storyboard)"}, {"format_id": "sb0", "format_note": "storyboard", "ext": "mhtml", "protocol": "mhtml", "acodec": "none", "vcodec": "none", "url": "https://d2nvs31859zcd8.cloudfront.net/89a8bdc0bb1f80665b01_reckful_26337123088_714740384/storyboards/177393650-high-0.jpg", "width": 220, "height": 124, "fps": 0.020928503133963668, "rows": 10, "columns": 5, "fragments": [{"url": "https://d2nvs31859zcd8.cloudfront.net/89a8bdc0bb1f80665b01_reckful_26337123088_714740384/storyboards/177393650-high-0.jpg", "duration": 2353.25}, {"url": "https://d2nvs31859zcd8.cloudfront.net/89a8bdc0bb1f80665b01_reckful_26337123088_714740384/storyboards/177393650-high-1.jpg", "duration": 2353.25}, {"url": "https://d2nvs31859zcd8.cloudfront.net/89a8bdc0bb1f80665b01_reckful_26337123088_714740384/storyboards/177393650-high-2.jpg", "duration": 2353.25}, {"url": "https://d2nvs31859zcd8.cloudfront.net/89a8bdc0bb1f80665b01_reckful_26337123088_714740384/storyboards/177393650-high-3.jpg", "duration": 2353.25}], "resolution": "220x124", "aspect_ratio": 1.77, "http_headers": {"User-Agent": "Mozilla/5.0 (Windows NT 10.0; Win64; x64) AppleWebKit/537.36 (KHTML, like Gecko) Chrome/94.0.4606.54 Safari/537.36", "Accept": "text/html,application/xhtml+xml,application/xml;q=0.9,*/*;q=0.8", "Accept-Language": "en-us,en;q=0.5", "Sec-Fetch-Mode": "navigate"}, "audio_ext": "none", "video_ext": "none", "format": "sb0 - 220x124 (storyboard)"}, {"format_id": "Audio_Only", "url": "https://dqrpb9wgowsf5.cloudfront.net/89a8bdc0bb1f80665b01_reckful_26337123088_714740384/audio_only/index-dvr.m3u8", "manifest_url": "https://usher.ttvnw.net/vod/177393650.m3u8?allow_source=true&allow_audio_only=true&allow_spectre=true&player=twitchweb&playlist_include_framerate=true&nauth=%7B%22authorization%22%3A%7B%22forbidden%22%3Afalse%2C%22reason%22%3A%22%22%7D%2C%22chansub%22%3A%7B%22restricted_bitrates%22%3A%5B%5D%7D%2C%22device_id%22%3Anull%2C%22expires%22%3A1681051292%2C%22https_required%22%3Atrue%2C%22privileged%22%3Afalse%2C%22user_id%22%3Anull%2C%22version%22%3A2%2C%22vod_id%22%3A177393650%7D&nauthsig=31b124bf7a66aa1621364a9c5db4ce28f0d46922", "tbr": 196.952, "ext": "mp4", "protocol": "m3u8_native", "vcodec": "none", "acodec": "mp4a.40.2", "resolution": "audio only", "filesize_approx": 237300374, "http_headers": {"User-Agent": "Mozilla/5.0 (Windows NT 10.0; Win64; x64) AppleWebKit/537.36 (KHTML, like Gecko) Chrome/94.0.4606.54 Safari/537.36", "Accept": "text/html,application/xhtml+xml,application/xml;q=0.9,*/*;q=0.8", "Accept-Language": "en-us,en;q=0.5", "Sec-Fetch-Mode": "navigate"}, "audio_ext": "mp4", "video_ext": "none", "abr": 196.952, "format": "Audio_Only - audio only"}, {"format_id": "160p", "url": "https://dqrpb9wgowsf5.cloudfront.net/89a8bdc0bb1f80665b01_reckful_26337123088_714740384/160p30/index-dvr.m3u8", "manifest_url": "https://usher.ttvnw.net/vod/177393650.m3u8?allow_source=true&allow_audio_only=true&allow_spectre=true&player=twitchweb&playlist_include_framerate=true&nauth=%7B%22authorization%22%3A%7B%22forbidden%22%3Afalse%2C%22reason%22%3A%22%22%7D%2C%22chansub%22%3A%7B%22restricted_bitrates%22%3A%5B%5D%7D%2C%22device_id%22%3Anull%2C%22expires%22%3A1681051292%2C%22https_required%22%3Atrue%2C%22privileged%22%3Afalse%2C%22user_id%22%3Anull%2C%22version%22%3A2%2C%22vod_id%22%3A177393650%7D&nauthsig=31b124bf7a66aa1621364a9c5db4ce28f0d46922", "tbr": 256.697, "ext": "mp4", "fps": 26.05, "protocol": "m3u8_native", "width": 284, "height": 160, "vcodec": "avc1.4D400C", "acodec": "mp4a.40.2", "dynamic_range": "SDR", "resolution": "284x160", "aspect_ratio": 1.77, "filesize_approx": 309284974, "http_headers": {"User-Agent": "Mozilla/5.0 (Windows NT 10.0; Win64; x64) AppleWebKit/537.36 (KHTML, like Gecko) Chrome/94.0.4606.54 Safari/537.36", "Accept": "text/html,application/xhtml+xml,application/xml;q=0.9,*/*;q=0.8", "Accept-Language": "en-us,en;q=0.5", "Sec-Fetch-Mode": "navigate"}, "video_ext": "mp4", "audio_ext": "none", "vbr": 256.697, "abr": 0.0, "format": "160p - 284x160"}, {"format_id": "360p", "url": "https://dqrpb9wgowsf5.cloudfront.net/89a8bdc0bb1f80665b01_reckful_26337123088_714740384/360p30/index-dvr.m3u8", "manifest_url": "https://usher.ttvnw.net/vod/177393650.m3u8?allow_source=true&allow_audio_only=true&allow_spectre=true&player=twitchweb&playlist_include_framerate=true&nauth=%7B%22authorization%22%3A%7B%22forbidden%22%3Afalse%2C%22reason%22%3A%22%22%7D%2C%22chansub%22%3A%7B%22restricted_bitrates%22%3A%5B%5D%7D%2C%22device_id%22%3Anull%2C%22expires%22%3A1681051292%2C%22https_required%22%3Atrue%2C%22privileged%22%3Afalse%2C%22user_id%22%3Anull%2C%22version%22%3A2%2C%22vod_id%22%3A177393650%7D&nauthsig=31b124bf7a66aa1621364a9c5db4ce28f0d46922", "tbr": 665.429, "ext": "mp4", "fps": 26.05, "protocol": "m3u8_native", "width": 640, "height": 360, "vcodec": "avc1.4D401E", "acodec": "mp4a.40.2", "dynamic_range": "SDR", "resolution": "640x360", "aspect_ratio": 1.78, "filesize_approx": 801751446, "http_headers": {"User-Agent": "Mozilla/5.0 (Windows NT 10.0; Win64; x64) AppleWebKit/537.36 (KHTML, like Gecko) Chrome/94.0.4606.54 Safari/537.36", "Accept": "text/html,application/xhtml+xml,application/xml;q=0.9,*/*;q=0.8", "Accept-Language": "en-us,en;q=0.5", "Sec-Fetch-Mode": "navigate"}, "video_ext": "mp4", "audio_ext": "none", "vbr": 665.429, "abr": 0.0, "format": "360p - 640x360"}, {"format_id": "480p", "url": "https://dqrpb9wgowsf5.cloudfront.net/89a8bdc0bb1f80665b01_reckful_26337123088_714740384/480p30/index-dvr.m3u8", "manifest_url": "https://usher.ttvnw.net/vod/177393650.m3u8?allow_source=true&allow_audio_only=true&allow_spectre=true&player=twitchweb&playlist_include_framerate=true&nauth=%7B%22authorization%22%3A%7B%22forbidden%22%3Afalse%2C%22reason%22%3A%22%22%7D%2C%22chansub%22%3A%7B%22restricted_bitrates%22%3A%5B%5D%7D%2C%22device_id%22%3Anull%2C%22expires%22%3A1681051292%2C%22https_required%22%3Atrue%2C%22privileged%22%3Afalse%2C%22user_id%22%3Anull%2C%22version%22%3A2%2C%22vod_id%22%3A177393650%7D&nauthsig=31b124bf7a66aa1621364a9c5db4ce28f0d46922", "tbr": 1376.0, "ext": "mp4", "fps": 26.05, "protocol": "m3u8_native", "width": 852, "height": 480, "vcodec": "avc1.4D401E", "acodec": "mp4a.40.2", "dynamic_range": "SDR", "resolution": "852x480", "aspect_ratio": 1.77, "filesize_approx": 1657892864, "http_headers": {"User-Agent": "Mozilla/5.0 (Windows NT 10.0; Win64; x64) AppleWebKit/537.36 (KHTML, like Gecko) Chrome/94.0.4606.54 Safari/537.36", "Accept": "text/html,application/xhtml+xml,application/xml;q=0.9,*/*;q=0.8", "Accept-Language": "en-us,en;q=0.5", "Sec-Fetch-Mode": "navigate"}, "video_ext": "mp4", "audio_ext": "none", "vbr": 1376.0, "abr": 0.0, "format": "480p - 852x480"}, {"format_id": "720p-0", "url": "https://dqrpb9wgowsf5.cloudfront.net/89a8bdc0bb1f80665b01_reckful_26337123088_714740384/720p30/index-dvr.m3u8", "manifest_url": "https://usher.ttvnw.net/vod/177393650.m3u8?allow_source=true&allow_audio_only=true&allow_spectre=true&player=twitchweb&playlist_include_framerate=true&nauth=%7B%22authorization%22%3A%7B%22forbidden%22%3Afalse%2C%22reason%22%3A%22%22%7D%2C%22chansub%22%3A%7B%22restricted_bitrates%22%3A%5B%5D%7D%2C%22device_id%22%3Anull%2C%22expires%22%3A1681051292%2C%22https_required%22%3Atrue%2C%22privileged%22%3Afalse%2C%22user_id%22%3Anull%2C%22version%22%3A2%2C%22vod_id%22%3A177393650%7D&nauthsig=31b124bf7a66aa1621364a9c5db4ce28f0d46922", "tbr": 2272.915, "ext": "mp4", "fps": 26.05, "protocol": "m3u8_native", "width": 1280, "height": 720, "vcodec": "avc1.4D401F", "acodec": "mp4a.40.2", "dynamic_range": "SDR", "resolution": "1280x720", "aspect_ratio": 1.78, "filesize_approx": 2738553458, "http_headers": {"User-Agent": "Mozilla/5.0 (Windows NT 10.0; Win64; x64) AppleWebKit/537.36 (KHTML, like Gecko) Chrome/94.0.4606.54 Safari/537.36", "Accept": "text/html,application/xhtml+xml,application/xml;q=0.9,*/*;q=0.8", "Accept-Language": "en-us,en;q=0.5", "Sec-Fetch-Mode": "navigate"}, "video_ext": "mp4", "audio_ext": "none", "vbr": 2272.915, "abr": 0.0, "format": "720p-0 - 1280x720"}, {"format_id": "720p-1", "url": "https://dqrpb9wgowsf5.cloudfront.net/89a8bdc0bb1f80665b01_reckful_26337123088_714740384/chunked/index-dvr.m3u8", "manifest_url": "https://usher.ttvnw.net/vod/177393650.m3u8?allow_source=true&allow_audio_only=true&allow_spectre=true&player=twitchweb&playlist_include_framerate=true&nauth=%7B%22authorization%22%3A%7B%22forbidden%22%3Afalse%2C%22reason%22%3A%22%22%7D%2C%22chansub%22%3A%7B%22restricted_bitrates%22%3A%5B%5D%7D%2C%22device_id%22%3Anull%2C%22expires%22%3A1681051292%2C%22https_required%22%3Atrue%2C%22privileged%22%3Afalse%2C%22user_id%22%3Anull%2C%22version%22%3A2%2C%22vod_id%22%3A177393650%7D&nauthsig=31b124bf7a66aa1621364a9c5db4ce28f0d46922", "tbr": 2691.143, "ext": "mp4", "fps": 29.959, "protocol": "m3u8_native", "quality": 10, "width": 1280, "height": 720, "vcodec": "avc1.42001F", "acodec": "mp4a.40.2", "dynamic_range": "SDR", "format_note": "Source", "resolution": "1280x720", "aspect_ratio": 1.78, "filesize_approx": 3242461319, "http_headers": {"User-Agent": "Mozilla/5.0 (Windows NT 10.0; Win64; x64) AppleWebKit/537.36 (KHTML, like Gecko) Chrome/94.0.4606.54 Safari/537.36", "Accept": "text/html,application/xhtml+xml,application/xml;q=0.9,*/*;q=0.8", "Accept-Language": "en-us,en;q=0.5", "Sec-Fetch-Mode": "navigate"}, "video_ext": "mp4", "audio_ext": "none", "vbr": 2691.143, "abr": 0.0, "format": "720p-1 - 1280x720 (Source)"}], "subtitles": {"rechat": [{"url": "https://api.twitch.tv/v5/videos/177393650/comments?client_id=kimne78kx3ncx6brgo4mv6wki5h1ko", "ext": "json"}]}, "webpage_url": "https://www.twitch.tv/videos/177393650", "webpage_url_basename": "177393650", "webpage_url_domain": "twitch.tv", "extractor": "twitch:vod", "extractor_key": "TwitchVod", "thumbnails": [{"url": "https://static-cdn.jtvnw.net/cf_vods/d2nvs31859zcd8/89a8bdc0bb1f80665b01_reckful_26337123088_714740384/thumb/thumb0-90x60.jpg", "id": "0"}], "display_id": "v177393650", "fulltitle": "Reckful - Barcelona, Spain last day", "duration_string": "2:36:53", "upload_date": "20170925", "live_status": "was_live", "format_id": "720p-1", "url": "https://dqrpb9wgowsf5.cloudfront.net/89a8bdc0bb1f80665b01_reckful_26337123088_714740384/chunked/index-dvr.m3u8", "manifest_url": "https://usher.ttvnw.net/vod/177393650.m3u8?allow_source=true&allow_audio_only=true&allow_spectre=true&player=twitchweb&playlist_include_framerate=true&nauth=%7B%22authorization%22%3A%7B%22forbidden%22%3Afalse%2C%22reason%22%3A%22%22%7D%2C%22chansub%22%3A%7B%22restricted_bitrates%22%3A%5B%5D%7D%2C%22device_id%22%3Anull%2C%22expires%22%3A1681051292%2C%22https_required%22%3Atrue%2C%22privileged%22%3Afalse%2C%22user_id%22%3Anull%2C%22version%22%3A2%2C%22vod_id%22%3A177393650%7D&nauthsig=31b124bf7a66aa1621364a9c5db4ce28f0d46922", "tbr": 2691.143, "ext": "mp4", "fps": 29.959, "protocol": "m3u8_native", "quality": 10, "width": 1280, "height": 720, "vcodec": "avc1.42001F", "acodec": "mp4a.40.2", "dynamic_range": "SDR", "format_note": "Source", "resolution": "1280x720", "aspect_ratio": 1.78, "filesize_approx": 3242461319, "http_headers": {"User-Agent": "Mozilla/5.0 (Windows NT 10.0; Win64; x64) AppleWebKit/537.36 (KHTML, like Gecko) Chrome/94.0.4606.54 Safari/537.36", "Accept": "text/html,application/xhtml+xml,application/xml;q=0.9,*/*;q=0.8", "Accept-Language": "en-us,en;q=0.5", "Sec-Fetch-Mode": "navigate"}, "video_ext": "mp4", "audio_ext": "none", "vbr": 2691.143, "abr": 0.0, "format": "720p-1 - 1280x720 (Source)", "epoch": 1680979293, "_type": "video", "_version": {"version": "2023.03.04", "release_git_head": "392389b7df7b818f794b231f14dc396d4875fbad", "repository": "yt-dlp/yt-dlp"}}